mwtab/__init__.py
mwtab/__main__.py
mwtab/_version.py
mwtab/cli.py
mwtab/converter.py
mwtab/duplicates_dict.py
mwtab/fileio.py
mwtab/metadata_column_matching.py
mwtab/mwextract.py
mwtab/mwrest.py
mwtab/mwschema.py
mwtab/mwtab.py
mwtab/tokenizer.py
mwtab/validator.py
mwtab-2.0.0.dist-info/licenses/LICENSE
mwtab-2.0.0.dist-info/METADATA
mwtab-2.0.0.dist-info/WHEEL
mwtab-2.0.0.dist-info/entry_points.txt
mwtab-2.0.0.dist-info/top_level.txt
mwtab-2.0.0.dist-info/RECORD
