Metadata-Version: 2.4
Name: mwtab
Version: 2.0.0
Summary: Parser for mwtab files from the Metabolomics Workbench
License: The Clear BSD License
Project-URL: Homepage, https://github.com/MoseleyBioinformaticsLab/mwtab
Project-URL: Documentation, https://moseleybioinformaticslab.github.io/mwtab/
Project-URL: GitHub, https://github.com/MoseleyBioinformaticsLab/mwtab
Project-URL: Issues, https://github.com/MoseleyBioinformaticsLab/mwtab/issues
Keywords: mwtab,metabolomics workbench
Classifier: Environment :: Console
Classifier: Intended Audience :: Developers
Classifier: Intended Audience :: Science/Research
Classifier: License :: OSI Approved :: BSD License
Classifier: Operating System :: OS Independent
Classifier: Programming Language :: Python :: 3.10
Classifier: Programming Language :: Python :: 3.11
Classifier: Programming Language :: Python :: 3.12
Classifier: Programming Language :: Python :: 3.13
Classifier: Programming Language :: Python :: 3.14
Classifier: Topic :: Scientific/Engineering :: Bio-Informatics
Classifier: Topic :: Software Development :: Libraries :: Python Modules
Requires-Python: >=3.10
License-File: LICENSE
Requires-Dist: docopt>=0.6.2
Requires-Dist: jsonschema>=4.18.6
Requires-Dist: pandas>=2.2.3
Requires-Dist: setuptools_scm>=7.0.5
Requires-Dist: pyarrow>=19.0.0
Dynamic: license-file
